imagesearch/__init__.py
imagesearch/__main__.py
imagesearch/algo.py
imagesearch/cli/__init__.py
imagesearch/cli/command.py
imagesearch/cli/format.py
imagesearch/cli/parser.py
imagesearch/compare.py
imagesearch/dupe.py
imagesearch/exceptions.py
imagesearch/fingerprint.py
imagesearch/progress.py
imagesearch/status.py
imagesearch-0.4.2.dist-info/entry_points.txt
imagesearch-0.4.2.dist-info/WHEEL
imagesearch-0.4.2.dist-info/METADATA
imagesearch-0.4.2.dist-info/RECORD
