Metadata-Version: 2.1
Name: imagesearch
Version: 0.4.2
Summary: Measure visual similiarity of a reference image to other images.
Home-page: https://github.com/t-mart/imagesearch
Author: Tim Martin
Author-email: tim@timmart.in
Requires-Python: >=3.8,<4.0
Classifier: Programming Language :: Python :: 3
Classifier: Programming Language :: Python :: 3.8
Requires-Dist: attrs (>=19.3.0,<20.0.0)
Requires-Dist: imagehash (>=4.1.0,<5.0.0)
Requires-Dist: tqdm (>=4.48.2,<5.0.0)
Project-URL: Repository, https://github.com/t-mart/imagesearch
